{
    "form_data": { /* 表单数据 */
        "birthYear": "1989", /* 出生年 */
        "divinationType": "婚恋", /* 占类 */
        "firstName": "姚", /* 姓 */
        "gender": "女", /* 性别 */
        "lastName": "宁", /* 名 */
        "location": "浙江·余姚", /* 属地 */
        "question": "能胜到吗", /* 占题 */
        "subType": "追男" /* 自建子类 */
    },
    "method": "number", /* 起卦方法 */
    "numbers": [ /* 起卦数字 */
        "510",
        "122",
        "417",
        "806",
        "276",
        "120"
    ],
    "time": { /* 占卜时间 */
        "day": 2, /* 日 */
        "hour": 19, /* 时 */
        "minute": 54, /* 分 */
        "month": 9, /* 月 */
        "second": 34, /* 秒 */
        "year": 2005 /* 年 */
    }
}